{
    "os": "Linux-6.5.0-15-generic-x86_64-with-glibc2.17",
    "python": "3.8.18",
    "heartbeatAt": "2024-01-29T12:34:29.945481",
    "startedAt": "2024-01-29T12:34:28.303252",
    "docker": null,
    "cuda": null,
    "args": [],
    "state": "running",
    "program": "SAC.py",
    "codePathLocal": "SAC.py",
    "codePath": "DeepRL_Study/SAC.py",
    "git": {
        "remote": "git@github.com:leejoonpyoo/RL_Study.git",
        "commit": "2949530a2591de45f5653cf57e8386fe6e3dd661"
    },
    "email": "leejoonpyoo@kaist.ac.kr",
    "root": "/home/junpyolee/git_repository/RL_Study",
    "host": "junpyolee-linux-server",
    "username": "junpyolee",
    "executable": "/home/junpyolee/anaconda3/envs/kotorch/bin/python",
    "cpu_count": 12,
    "cpu_count_logical": 24,
    "cpu_freq": {
        "current": 2841.3976249999996,
        "min": 2200.0,
        "max": 3700.0
    },
    "cpu_freq_per_core": [
        {
            "current": 3582.847,
            "min": 2200.0,
            "max": 3700.0
        },
        {
            "current": 2874.47,
            "min": 2200.0,
            "max": 3700.0
        },
        {
            "current": 2200.0,
            "min": 2200.0,
            "max": 3700.0
        },
        {
            "current": 2200.0,
            "min": 2200.0,
            "max": 3700.0
        },
        {
            "current": 2200.0,
            "min": 2200.0,
            "max": 3700.0
        },
        {
            "current": 2200.0,
            "min": 2200.0,
            "max": 3700.0
        },
        {
            "current": 3777.926,
            "min": 2200.0,
            "max": 3700.0
        },
        {
            "current": 4659.201,
            "min": 2200.0,
            "max": 3700.0
        },
        {
            "current": 3042.323,
            "min": 2200.0,
            "max": 3700.0
        },
        {
            "current": 2200.0,
            "min": 2200.0,
            "max": 3700.0
        },
        {
            "current": 2200.0,
            "min": 2200.0,
            "max": 3700.0
        },
        {
            "current": 3798.329,
            "min": 2200.0,
            "max": 3700.0
        },
        {
            "current": 3592.728,
            "min": 2200.0,
            "max": 3700.0
        },
        {
            "current": 2874.762,
            "min": 2200.0,
            "max": 3700.0
        },
        {
            "current": 2200.0,
            "min": 2200.0,
            "max": 3700.0
        },
        {
            "current": 2200.0,
            "min": 2200.0,
            "max": 3700.0
        },
        {
            "current": 2200.0,
            "min": 2200.0,
            "max": 3700.0
        },
        {
            "current": 2200.0,
            "min": 2200.0,
            "max": 3700.0
        },
        {
            "current": 3766.872,
            "min": 2200.0,
            "max": 3700.0
        },
        {
            "current": 4704.963,
            "min": 2200.0,
            "max": 3700.0
        },
        {
            "current": 2876.776,
            "min": 2200.0,
            "max": 3700.0
        },
        {
            "current": 4561.267,
            "min": 2200.0,
            "max": 3700.0
        },
        {
            "current": 3775.863,
            "min": 2200.0,
            "max": 3700.0
        },
        {
            "current": 3836.424,
            "min": 2200.0,
            "max": 3700.0
        }
    ],
    "disk": {
        "/": {
            "total": 915.3213348388672,
            "used": 85.09383392333984
        }
    },
    "gpu": "NVIDIA GeForce RTX 4070",
    "gpu_count": 1,
    "gpu_devices": [
        {
            "name": "NVIDIA GeForce RTX 4070",
            "memory_total": 12878610432
        }
    ],
    "memory": {
        "total": 62.69356155395508
    }
}
